ad/__init__.py
ad/activation_ops.py
ad/ad.py
ad/simple_ops.py
AutoDiffX-0.2.dist-info/LICENSE
AutoDiffX-0.2.dist-info/METADATA
AutoDiffX-0.2.dist-info/WHEEL
AutoDiffX-0.2.dist-info/top_level.txt
AutoDiffX-0.2.dist-info/RECORD
