Metadata-Version: 2.1
Name: AutoDiffX
Version: 0.2
Summary: Lightweight Package for Automatic Differentiation
Home-page: https://github.com/CS207-Project-Team-1/cs207-FinalProject/
Author: William Fu
Author-email: wfu@college.harvard.edu
License: MIT
Project-URL: Bug Tracker, https://github.com/CS207-Project-Team-1/cs207-FinalProject/
Project-URL: Documentation, https://github.com/CS207-Project-Team-1/cs207-FinalProject/
Project-URL: Source Code, https://github.com/CS207-Project-Team-1/cs207-FinalProject/
Keywords: automatic differentiation,differentiation
Platform: UNKNOWN
